fire_env_extension/__init__.py
fire_env_extension/env_ext.py
fire_env_extension-0.0.4.dist-info/LICENSE
fire_env_extension-0.0.4.dist-info/METADATA
fire_env_extension-0.0.4.dist-info/WHEEL
fire_env_extension-0.0.4.dist-info/top_level.txt
fire_env_extension-0.0.4.dist-info/RECORD
